docwmd/__init__.py
docwmd-0.0.6.dist-info/LICENSE
docwmd-0.0.6.dist-info/METADATA
docwmd-0.0.6.dist-info/WHEEL
docwmd-0.0.6.dist-info/top_level.txt
docwmd-0.0.6.dist-info/RECORD
