Metadata-Version: 2.1
Name: docwmd
Version: 0.0.6
Summary: A small package using wmd to get closet doc to a chosen doc
Home-page: https://gitlab.com/guillaume.burgaud.name/smd
Author: Alice Petit, Nolwenn Sourice
License: UNKNOWN
Platform: UNKNOWN
Classifier: Programming Language :: Python :: 3
Classifier: License :: OSI Approved :: MIT License
Classifier: Operating System :: OS Independent
Requires-Python: >=3.6
